aira/__init__.py
aira/aira.py
aira/cli.py
aira/commit_manager.py
aira/repository_manager.py
aira/utils.py
aira-0.5.0.dist-info/LICENSE
aira-0.5.0.dist-info/METADATA
aira-0.5.0.dist-info/WHEEL
aira-0.5.0.dist-info/entry_points.txt
aira-0.5.0.dist-info/top_level.txt
aira-0.5.0.dist-info/RECORD
