Metadata-Version: 2.2
Name: aira
Version: 0.5.0
Home-page: https://github.com/your_username/aira
Classifier: Development Status :: 3 - Alpha
Classifier: Intended Audience :: Developers
Classifier: Topic :: Software Development :: Version Control
License-File: LICENSE
Requires-Dist: python-dotenv
Requires-Dist: termcolor
Requires-Dist: art
Requires-Dist: loguru
Requires-Dist: tqdm
Requires-Dist: harmon_ai
Requires-Dist: gaiah_toolkit
Requires-Dist: litellm
Requires-Dist: google-generativeai
Dynamic: classifier
Dynamic: description
Dynamic: description-content-type
Dynamic: home-page
Dynamic: requires-dist
